Metadata-Version: 2.4
Name: pybestlib
Version: 0.3.1
Summary: BestLib, the best lib for graphics - Interactive dashboards for Jupyter with D3.js
Home-page: https://github.com/NahiaEscalante/bestlib
Author: Nahia Escalante, Alejandro Rojas y Max Antúnez
Author-email: 
License: MIT
Project-URL: Homepage, https://github.com/NahiaEscalante/bestlib
Project-URL: Documentation, https://github.com/NahiaEscalante/bestlib#readme
Project-URL: Repository, https://github.com/NahiaEscalante/bestlib
Project-URL: Bug Reports, https://github.com/NahiaEscalante/bestlib/issues
Keywords: visualization,dashboard,d3.js,jupyter,interactive,charts,data-visualization
Classifier: Development Status :: 3 - Alpha
Classifier: Intended Audience :: Developers
Classifier: Intended Audience :: Science/Research
Classifier: Topic :: Scientific/Engineering :: Visualization
Classifier: License :: OSI Approved :: MIT License
Classifier: Programming Language :: Python :: 3
Classifier: Programming Language :: Python :: 3.8
Classifier: Programming Language :: Python :: 3.9
Classifier: Programming Language :: Python :: 3.10
Classifier: Programming Language :: Python :: 3.11
Classifier: Programming Language :: Python :: 3.12
Classifier: Framework :: Jupyter
Requires-Python: >=3.8
License-File: LICENSE
Requires-Dist: ipython>=7.34.0
Requires-Dist: ipykernel>=6.0
Requires-Dist: ipywidgets>=7.0
Requires-Dist: traitlets>=5.0
Requires-Dist: pandas>=1.3
Requires-Dist: numpy>=1.20
Requires-Dist: scipy>=1.8
Provides-Extra: jupyter
Requires-Dist: jupyterlab>=4.0; extra == "jupyter"
Requires-Dist: notebook>=6.0; extra == "jupyter"
Provides-Extra: ml
Requires-Dist: scikit-learn>=1.0; extra == "ml"
Dynamic: home-page
Dynamic: license-file
Dynamic: requires-python
